[
null,
{"id":1,"animationId":-1,"damage":{"critical":true,"elementId":-1,"formula":"a.atk * 4 - b.def * 2","type":1,"variance":20},"description":"","effects":[{"code":21,"dataId":0,"value1":1,"value2":0}],"hitType":1,"iconIndex":76,"message1":"の攻撃！","message2":"","mpCost":0,"name":"攻撃","note":"スキル１番は［攻撃］コマンドを\n選択したときに使用されます。","occasion":1,"repeats":1,"requiredWtypeId1":0,"requiredWtypeId2":0,"scope":1,"speed":0,"stypeId":0,"successRate":100,"tpCost":0,"tpGain":10},
{"id":2,"animationId":0,"damage":{"critical":false,"elementId":0,"formula":"0","type":0,"variance":20},"description":"","effects":[{"code":21,"dataId":2,"value1":1,"value2":0}],"hitType":0,"iconIndex":81,"message1":"は身を守っている。","message2":"","mpCost":0,"name":"防御","note":"スキル２番は［防御］コマンドを\n選択したときに使用されます。","occasion":1,"repeats":1,"requiredWtypeId1":0,"requiredWtypeId2":0,"scope":11,"speed":2000,"stypeId":0,"successRate":100,"tpCost":0,"tpGain":10},
{"id":3,"animationId":-1,"damage":{"critical":true,"elementId":-1,"formula":"a.atk * 4 - b.def * 2","type":1,"variance":20},"description":"","effects":[{"code":21,"dataId":0,"value1":1,"value2":0}],"hitType":1,"iconIndex":76,"message1":"の攻撃！","message2":"","mpCost":0,"name":"連続攻撃","note":"","occasion":1,"repeats":2,"requiredWtypeId1":0,"requiredWtypeId2":0,"scope":1,"speed":0,"stypeId":0,"successRate":100,"tpCost":0,"tpGain":5},
{"id":4,"animationId":-1,"damage":{"critical":true,"elementId":-1,"formula":"a.atk * 4 - b.def * 2","type":1,"variance":20},"description":"","effects":[{"code":21,"dataId":0,"value1":1,"value2":0}],"hitType":1,"iconIndex":76,"message1":"の攻撃！","message2":"","mpCost":0,"name":"２回攻撃","note":"","occasion":1,"repeats":1,"requiredWtypeId1":0,"requiredWtypeId2":0,"scope":4,"speed":0,"stypeId":2,"successRate":100,"tpCost":0,"tpGain":5},
{"id":5,"animationId":-1,"damage":{"critical":true,"elementId":-1,"formula":"a.atk * 4 - b.def * 2","type":1,"variance":20},"description":"","effects":[{"code":21,"dataId":0,"value1":1,"value2":0}],"hitType":1,"iconIndex":76,"message1":"の攻撃！","message2":"","mpCost":0,"name":"３回攻撃","note":"","occasion":1,"repeats":1,"requiredWtypeId1":0,"requiredWtypeId2":0,"scope":5,"speed":0,"stypeId":2,"successRate":100,"tpCost":0,"tpGain":4},
{"id":6,"animationId":0,"damage":{"critical":false,"elementId":0,"formula":"0","type":0,"variance":20},"description":"","effects":[{"code":41,"dataId":0,"value1":0,"value2":0}],"hitType":0,"iconIndex":82,"message1":"は逃げてしまった。","message2":"","mpCost":0,"name":"逃げる","note":"","occasion":1,"repeats":1,"requiredWtypeId1":0,"requiredWtypeId2":0,"scope":11,"speed":0,"stypeId":0,"successRate":100,"tpCost":0,"tpGain":0},
{"id":7,"animationId":0,"damage":{"critical":false,"elementId":0,"formula":"0","type":0,"variance":20},"description":"","effects":[],"hitType":0,"iconIndex":81,"message1":"は様子を見ている。","message2":"","mpCost":0,"name":"様子を見る","note":"","occasion":1,"repeats":1,"requiredWtypeId1":0,"requiredWtypeId2":0,"scope":0,"speed":0,"stypeId":0,"successRate":100,"tpCost":0,"tpGain":10},
{"id":8,"animationId":41,"damage":{"critical":false,"elementId":0,"formula":"200 + a.mat","type":3,"variance":20},"description":"","effects":[],"hitType":0,"iconIndex":72,"message1":"は%1を唱えた！","message2":"","mpCost":5,"name":"ヒール","note":"","occasion":0,"repeats":1,"requiredWtypeId1":0,"requiredWtypeId2":0,"scope":7,"speed":0,"stypeId":1,"successRate":100,"tpCost":0,"tpGain":10},
{"id":9,"animationId":66,"damage":{"critical":false,"elementId":2,"formula":"100 + a.mat * 2 - b.mdf * 2","type":1,"variance":20},"description":"","effects":[],"hitType":2,"iconIndex":64,"message1":"は%1を唱えた！","message2":"","mpCost":5,"name":"ファイア","note":"","occasion":1,"repeats":1,"requiredWtypeId1":0,"requiredWtypeId2":0,"scope":1,"speed":0,"stypeId":1,"successRate":100,"tpCost":0,"tpGain":10},
{"id":10,"animationId":78,"damage":{"critical":false,"elementId":4,"formula":"100 + a.mat * 2 - b.mdf * 2","type":1,"variance":20},"description":"","effects":[],"hitType":2,"iconIndex":66,"message1":"は%1を唱えた！","message2":"","mpCost":5,"name":"スパーク","note":"","occasion":1,"repeats":1,"requiredWtypeId1":0,"requiredWtypeId2":0,"scope":2,"speed":0,"stypeId":1,"successRate":100,"tpCost":0,"tpGain":10},
{"id":11,"animationId":0,"damage":{"critical":false,"elementId":6,"formula":"100","type":1,"variance":20},"description":"英語の神髄。\n数学教師によく効く。","effects":[],"hitType":0,"iconIndex":230,"message1":"は%1を解放した！","message2":"","mpCost":0,"name":"英語の神髄","note":"","occasion":1,"repeats":1,"requiredWtypeId1":0,"requiredWtypeId2":0,"scope":1,"speed":0,"stypeId":1,"successRate":100,"tpCost":0,"tpGain":0},
{"id":12,"animationId":0,"damage":{"critical":false,"elementId":3,"formula":"100","type":1,"variance":20},"description":"数学の神髄。\n国語教師によく効く。","effects":[],"hitType":0,"iconIndex":234,"message1":"は%1を解放した！","message2":"","mpCost":0,"name":"数学の神髄","note":"","occasion":1,"repeats":1,"requiredWtypeId1":0,"requiredWtypeId2":0,"scope":1,"speed":0,"stypeId":1,"successRate":100,"tpCost":0,"tpGain":0},
{"id":13,"animationId":0,"damage":{"critical":false,"elementId":2,"formula":"100","type":1,"variance":20},"description":"国語の神髄。\n英語教師によく効く。","effects":[],"hitType":0,"iconIndex":231,"message1":"は%1を解放した！","message2":"","mpCost":0,"name":"国語の神髄","note":"","occasion":1,"repeats":1,"requiredWtypeId1":0,"requiredWtypeId2":0,"scope":1,"speed":0,"stypeId":1,"successRate":100,"tpCost":0,"tpGain":0},
{"id":14,"animationId":0,"damage":{"critical":false,"elementId":7,"formula":"100","type":1,"variance":20},"description":"理科の神髄。\n社会教師によく効く。","effects":[],"hitType":0,"iconIndex":233,"message1":"は%1を解放した！","message2":"","mpCost":0,"name":"理科の神髄","note":"","occasion":1,"repeats":1,"requiredWtypeId1":0,"requiredWtypeId2":0,"scope":1,"speed":0,"stypeId":1,"successRate":100,"tpCost":0,"tpGain":0},
{"id":15,"animationId":0,"damage":{"critical":false,"elementId":4,"formula":"100","type":1,"variance":20},"description":"社会の神髄。\n理科教師によく効く。","effects":[],"hitType":0,"iconIndex":232,"message1":"は%1を解放した！","message2":"","mpCost":0,"name":"社会の神髄","note":"","occasion":1,"repeats":1,"requiredWtypeId1":0,"requiredWtypeId2":0,"scope":1,"speed":0,"stypeId":1,"successRate":100,"tpCost":0,"tpGain":0},
{"id":16,"animationId":34,"damage":{"critical":false,"elementId":6,"formula":"20","type":1,"variance":20},"description":"surprise party","effects":[],"hitType":2,"iconIndex":68,"message1":"は%1を唱えた！","message2":"","mpCost":0,"name":"不意打ちのパーティー","note":"","occasion":0,"repeats":1,"requiredWtypeId1":0,"requiredWtypeId2":0,"scope":1,"speed":0,"stypeId":1,"successRate":100,"tpCost":0,"tpGain":0},
{"id":17,"animationId":0,"damage":{"critical":false,"elementId":6,"formula":"20","type":5,"variance":20},"description":"April fool","effects":[],"hitType":0,"iconIndex":68,"message1":"は%1を唱えた！","message2":"","mpCost":0,"name":"四月馬鹿","note":"","occasion":0,"repeats":1,"requiredWtypeId1":0,"requiredWtypeId2":0,"scope":1,"speed":0,"stypeId":1,"successRate":100,"tpCost":0,"tpGain":0},
{"id":18,"animationId":0,"damage":{"critical":false,"elementId":0,"formula":"9999","type":2,"variance":20},"description":"volunteer","effects":[],"hitType":0,"iconIndex":68,"message1":"は%1を唱えた！","message2":"","mpCost":0,"name":"有志の人々","note":"","occasion":0,"repeats":1,"requiredWtypeId1":0,"requiredWtypeId2":0,"scope":1,"speed":0,"stypeId":1,"successRate":100,"tpCost":0,"tpGain":0},
{"id":19,"animationId":0,"damage":{"critical":false,"elementId":0,"formula":"0","type":0,"variance":20},"description":"ばかもんっ\n相手は硬直することがある。","effects":[{"code":21,"dataId":6,"value1":0.4,"value2":0}],"hitType":0,"iconIndex":70,"message1":"は%1を唱えた！","message2":"","mpCost":0,"name":"ばかもんっ","note":"","occasion":0,"repeats":1,"requiredWtypeId1":0,"requiredWtypeId2":0,"scope":1,"speed":0,"stypeId":2,"successRate":100,"tpCost":0,"tpGain":0},
{"id":20,"animationId":57,"damage":{"critical":false,"elementId":0,"formula":"-20000","type":5,"variance":20},"description":"相手はショックで2ターン行動不能になることがある。\n使用者もダメージを受ける。","effects":[{"code":21,"dataId":10,"value1":1,"value2":0}],"hitType":0,"iconIndex":0,"message1":"は%1を唱えた！","message2":"","mpCost":0,"name":"死刑！！","note":"","occasion":0,"repeats":1,"requiredWtypeId1":0,"requiredWtypeId2":0,"scope":1,"speed":0,"stypeId":2,"successRate":60,"tpCost":0,"tpGain":0},
{"id":21,"animationId":0,"damage":{"critical":false,"elementId":0,"formula":"0","type":0,"variance":20},"description":"おすすめの本について長々と解説する。\n相手はHPの10%を削られ、50%の確率で寝る。","effects":[{"code":11,"dataId":0,"value1":-0.1,"value2":0},{"code":21,"dataId":10,"value1":0.5,"value2":0}],"hitType":0,"iconIndex":186,"message1":"は%1を唱えた！","message2":"","mpCost":0,"name":"名著です","note":"","occasion":0,"repeats":1,"requiredWtypeId1":0,"requiredWtypeId2":0,"scope":1,"speed":0,"stypeId":1,"successRate":100,"tpCost":0,"tpGain":0},
{"id":22,"animationId":0,"damage":{"critical":false,"elementId":0,"formula":"0","type":0,"variance":20},"description":"3ターンの間、攻撃力と防御力が上昇する。","effects":[{"code":31,"dataId":3,"value1":3,"value2":0},{"code":31,"dataId":2,"value1":3,"value2":0}],"hitType":0,"iconIndex":82,"message1":"は%1を実感した！","message2":"","mpCost":0,"name":"筋トレの成果","note":"","occasion":0,"repeats":1,"requiredWtypeId1":0,"requiredWtypeId2":0,"scope":7,"speed":0,"stypeId":1,"successRate":100,"tpCost":0,"tpGain":0},
{"id":23,"animationId":0,"damage":{"critical":false,"elementId":0,"formula":"0","type":0,"variance":20},"description":"駿台は素晴らしい。","effects":[{"code":31,"dataId":2,"value1":5,"value2":0}],"hitType":0,"iconIndex":84,"message1":"は%1を唱えた！","message2":"","mpCost":0,"name":"駿台さこー","note":"","occasion":1,"repeats":1,"requiredWtypeId1":0,"requiredWtypeId2":0,"scope":2,"speed":0,"stypeId":2,"successRate":100,"tpCost":0,"tpGain":0}
]